pynote/__init__.py
pynote/__main__.py
pynote/config.py
pynote/engine.py
pynote-69.420.dist-info/LICENSE
pynote-69.420.dist-info/METADATA
pynote-69.420.dist-info/WHEEL
pynote-69.420.dist-info/entry_points.txt
pynote-69.420.dist-info/top_level.txt
pynote-69.420.dist-info/RECORD
