Metadata-Version: 2.1
Name: pynote
Version: 69.420
Summary: Note taking app. OUTDATED.
Home-page: https://github.com/xdeafbabe/pynote
Author: 0xDEAFBABE
Author-email: deafbabe@startmail.com
License: UNKNOWN
Project-URL: Repository, https://github.com/xdeafbabe/pynote
Platform: UNKNOWN
Classifier: Programming Language :: Python :: 3
Classifier: Programming Language :: Python :: 3.9
Classifier: License :: OSI Approved :: MIT License
Requires-Python: >=3.9,<4
Requires-Dist: confboy (<1.0.0,>=0.2.0)
Requires-Dist: typer[all] (<1.0.0,>=0.3.0)
Provides-Extra: dev
Requires-Dist: flake8-commas (==2.0.0) ; extra == 'dev'
Requires-Dist: flake8-import-order (==0.18.1) ; extra == 'dev'
Requires-Dist: flake8-quotes (==3.2.0) ; extra == 'dev'
Requires-Dist: flake8 (==3.9.1) ; extra == 'dev'
Requires-Dist: pep8-naming (==0.11.1) ; extra == 'dev'
Provides-Extra: test
Requires-Dist: pytest-cov (==2.11.1) ; extra == 'test'
Requires-Dist: pytest-mock (==3.5.1) ; extra == 'test'
Requires-Dist: pytest (==6.2.2) ; extra == 'test'
